lateflat/__init__.py
lateflat/lateflat.py
lateflat-0.1.3.dist-info/licenses/LICENSE
lateflat-0.1.3.dist-info/METADATA
lateflat-0.1.3.dist-info/WHEEL
lateflat-0.1.3.dist-info/entry_points.txt
lateflat-0.1.3.dist-info/top_level.txt
lateflat-0.1.3.dist-info/RECORD
