Metadata-Version: 2.4
Name: lateflat
Version: 0.1.3
Summary: A command-line tool to flatten LaTeX projects into a single root directory for easy submission.
Author-email: Nkzono99 <j-nakazono@stu.kobe-u.ac.jp>
Maintainer-email: Nkzono99 <j-nakazono@stu.kobe-u.ac.jp>
License:                                  Apache License
Project-URL: Repository, https://github.com/Nkzono99/lateflat
Keywords: latex,project flattening,file organization
Classifier: License :: OSI Approved :: Apache Software License
Classifier: Development Status :: 3 - Alpha
Classifier: Programming Language :: Python :: 3
Classifier: Programming Language :: Python :: 3.7
Classifier: Programming Language :: Python :: 3.8
Classifier: Programming Language :: Python :: 3.9
Classifier: Topic :: Text Processing :: Markup :: LaTeX
Classifier: Intended Audience :: Developers
Classifier: Operating System :: OS Independent
Requires-Python: >=3.7
License-File: LICENSE
Dynamic: license-file
